seaq/__init__.py
seaq/core.py
seaq/sql/init.sql
seaq-0.0.4.dist-info/METADATA
seaq-0.0.4.dist-info/WHEEL
seaq-0.0.4.dist-info/top_level.txt
seaq-0.0.4.dist-info/RECORD
